{
  "Number": 48,
  "Name": "Գաղատացիս",
  "Chapters": [
    {
      "Number": 1,
      "Description": "Գաղատացիների փոփոխամտութիւնը աւետարանում, և Պօղոսի առաքելութիւնը։ ",
      "Verses": [
        {
          "Number": 1,
          "Content": " Պօղոս առաքեալ  ոչ թէ մարդկանցից եւ ոչ թէ մարդի ձեռով,  այլ Յիսուս Քրիստոսի եւ Հայր Աստուծոյ ձեռովը,  որ մեռելներից յարութիւն տուաւ նորան։ ",
          "ID": "b1t2b48c1v1",
          "intID": 1248001001
        },
        {
          "Number": 2,
          "Content": "  Եւ ամեն եղբարքը՝ որ ինձ հետ են.  Գաղատիայի եկեղեցիներիդ։ ",
          "ID": "b1t2b48c1v2",
          "intID": 1248001002
        },
        {
          "Number": 3,
          "Content": "  Շնորհք լինի ձեզ եւ խաղաղութիւն Հայր Աստուածանից եւ մեր Տէր Յիսուս Քրիստոսից, ",
          "ID": "b1t2b48c1v3",
          "intID": 1248001003
        },
        {
          "Number": 4,
          "Content": "  Որ իր անձը մեր մեղքերի համար տուաւ,  որ մեզ այս չար աշխարհքիցը փրկէ՝ Աստուծոյ եւ մեր Հօր կամքի պէս։ ",
          "ID": "b1t2b48c1v4",
          "intID": 1248001004
        },
        {
          "Number": 5,
          "Content": " Որին լինի փառք յաւիտեանս յաւիտենից. ամէն։ \n",
          "ID": "b1t2b48c1v5",
          "intID": 1248001005
        },
        {
          "Number": 6,
          "Content": " Զարմանում եմ որ այսպէս շուտով փոփոխվում էք  ձեզ Քրիստոսի շնորհքի մէջ կանչողից դէպի ուրիշ աւետարան։ ",
          "ID": "b1t2b48c1v6",
          "intID": 1248001006
        },
        {
          "Number": 7,
          "Content": "  Որ ուրիշը չկայ.  միայն թէ կան ոմանք որ ձեզ խռովեցնում են, եւ կամենում են Քրիստոսի աւետարանը փոխել։ ",
          "ID": "b1t2b48c1v7",
          "intID": 1248001007
        },
        {
          "Number": 8,
          "Content": "  Բայց եթէ մենք էլ, կամ երկնքիցը մի հրեշտակ աւետարանէ ձեզ նորանից ուրիշ քան թէ որ մենք աւետարանեցինք ձեզ, նզովուած լինի։ ",
          "ID": "b1t2b48c1v8",
          "intID": 1248001008
        },
        {
          "Number": 9,
          "Content": " Ինչպէս առաջ ասեցինք՝ եւ հիմա դարձեալ ասում եմ,  եթէ մէկն աւետարանէ ձեզ նորանից ուրիշ քան որ դուք առաք՝ նզովուած լինի։ ",
          "ID": "b1t2b48c1v9",
          "intID": 1248001009
        },
        {
          "Number": 10,
          "Content": "  Որովհետեւ հիմա  մարդկա՞նց եմ հաճեցնում, թէ Աստուծուն.  կամ ուզում եմ մարդկա՞նց հաճոյ լինել. եթէ տակաւին մարդկանց հաճոյ լինէի, Քրիստոսի ծառայ չէի։ \n",
          "ID": "b1t2b48c1v10",
          "intID": 1248001010
        },
        {
          "Number": 11,
          "Content": "  Իմացնում եմ ձեզ, եղբարք, այն աւետարանը, որ ինձանից աւետարանուեցաւ, որ նա մարդից չէ։ ",
          "ID": "b1t2b48c1v11",
          "intID": 1248001011
        },
        {
          "Number": 12,
          "Content": "  Որովհետեւ ես էլ ոչ մարդից առայ նորան, եւ ոչ էլ սովորեցի.  այլ Յիսուս Քրիստոսի յայտնութիւնովը։ ",
          "ID": "b1t2b48c1v12",
          "intID": 1248001012
        },
        {
          "Number": 13,
          "Content": " Վասնզի դուք իմ վարքը լսել էք, որ մի ժամանակ Հրէութեան մէջ էի.  որ չափիցը դուրս հալածում էի Աստուծոյ եկեղեցին,  եւ կործանում էի նորան։ ",
          "ID": "b1t2b48c1v13",
          "intID": 1248001013
        },
        {
          "Number": 14,
          "Content": " Եւ Հրէութեան մէջ իմ հասակակիցների շատերից յառաջադէմ էի իմ ազգի մէջ,  աւելի նախանձաւոր լինելով  իմ հայրենական աւանդութիւնների համար։ ",
          "ID": "b1t2b48c1v14",
          "intID": 1248001014
        },
        {
          "Number": 15,
          "Content": " Բայց երբոր բարեհաճեց Աստուած,  որ իմ մօր որովայնիցն ինձ որոշել եւ իր շնորհքովն կանչել է, ",
          "ID": "b1t2b48c1v15",
          "intID": 1248001015
        },
        {
          "Number": 16,
          "Content": "  Որ իր Որդին ինձանով յայտնէ.  որ նորան հեթանոսների միջումն աւետարանեմ. այն ժամանակ իսկոյն  մարմնի եւ արիւնի հետ խորհուրդ չարի. ",
          "ID": "b1t2b48c1v16",
          "intID": 1248001016
        },
        {
          "Number": 17,
          "Content": " Եւ ոչ էլ գնացի Երուսաղէմ նորանց մօտ, որ ինձանից առաջ առաքեալներ էին. այլ գնացի Արաբիա, եւ կրկին դարձայ Դամասկոս։ ",
          "ID": "b1t2b48c1v17",
          "intID": 1248001017
        },
        {
          "Number": 18,
          "Content": " Այնուհետեւ երեք տարուց յետոյ  գնացի Երուսաղէմ, Պետրոսին տեսնելու. եւ տասնեւհինգ օր նորա մօտ եղայ։ ",
          "ID": "b1t2b48c1v18",
          "intID": 1248001018
        },
        {
          "Number": 19,
          "Content": "  Եւ առաքեալներից մի ուրիշին չտեսայ,  բայց միայն Տիրոջ եղբայր Յակոբին։ ",
          "ID": "b1t2b48c1v19",
          "intID": 1248001019
        },
        {
          "Number": 20,
          "Content": " Բայց ինչ որ ձեզ գրում եմ,  ահա Աստուծոյ առաջին, որ սուտ չեմ ասում։ ",
          "ID": "b1t2b48c1v20",
          "intID": 1248001020
        },
        {
          "Number": 21,
          "Content": "  Յետոյ եկայ Սիւրիայի եւ Կիլիկիայի կողմերը։ ",
          "ID": "b1t2b48c1v21",
          "intID": 1248001021
        },
        {
          "Number": 22,
          "Content": "  Եւ երեսով անծանօթ էի Հրէաստանի եկեղեցիներին՝ որ Քրիստոսումն էին։ ",
          "ID": "b1t2b48c1v22",
          "intID": 1248001022
        },
        {
          "Number": 23,
          "Content": " Բայց միայն լսել էին, թէ Նա որ մի ժամանակ մեզ հալածում էր, հիմա այն հաւատքն է աւետարանում որ առաջ կործանում էր։ ",
          "ID": "b1t2b48c1v23",
          "intID": 1248001023
        },
        {
          "Number": 24,
          "Content": " Եւ ինձանով փառաւորում էին Աստուծուն։ \n",
          "ID": "b1t2b48c1v24",
          "intID": 1248001024
        }
      ],
      "ID": "b1t2b48c1",
      "intID": 1248001000,
      "HTML": null,
      "IsDownloaded": false,
      "IsProblematic": false,
      "Content": null
    },
    {
      "Number": 2,
      "Description": "Պօղոսի և Պետրոսի մէջ գաղափարի զանազանութիւն։ Հաւատքով արդարացում։ ",
      "Verses": [
        {
          "Number": 1,
          "Content": " Ապա տասնեւչորս տարուց յետոյ  դարձեալ գնացի Երուսաղէմ, Բառնաբասի հետ, եւ Տիտոսին էլ ինձ հետ առայ։ ",
          "ID": "b1t2b48c2v1",
          "intID": 1248002001
        },
        {
          "Number": 2,
          "Content": " Եւ գնացի յայտնութիւնով.  եւ նորանց իմացրի այն աւետարանը՝ որ քարոզում եմ հեթանոսների մէջ, եւ մասնաւորապէս նորանց՝ որ մեծ կարծուած էին.  որ չ’լինի թէ զուր տեղը վազեմ կամ վազած լինեմ։ ",
          "ID": "b1t2b48c2v2",
          "intID": 1248002002
        },
        {
          "Number": 3,
          "Content": " Բայց Տիտոսն էլ որ ինձ հետ էր՝ Հելլենացի լինելով, չ’բռնադատուեցաւ թլփատուելու։ ",
          "ID": "b1t2b48c2v3",
          "intID": 1248002003
        },
        {
          "Number": 4,
          "Content": "  Եւ այն ներս պրծած սուտ եղբայրների պատճառով, որ ներս պրծան  մեր ազատութիւնը լրտեսելու համար, որ Քրիստոս Յիսուսումն ունինք,  որ մեզ ծառայեցնեն։ ",
          "ID": "b1t2b48c2v4",
          "intID": 1248002004
        },
        {
          "Number": 5,
          "Content": " Որոնց մի ժամ էլ ականջ չ’դրինք՝ հնազանդ լինելու համար,  որ աւետարանի ճշմարտութիւնը ձեզանում հաստատ մնայ։ ",
          "ID": "b1t2b48c2v5",
          "intID": 1248002005
        },
        {
          "Number": 6,
          "Content": "  Բայց այն մեծ կարծուածների համար, թէ մի բան լինին, (թէ ինչ էին մի ժամանակ, նա ես հոգս չեմ անում.  Աստուած  աչառութիւն չէ անում.)  որ այն մեծ կարծուածներն այնպիսի բան չիմացրին ինձ։ ",
          "ID": "b1t2b48c2v6",
          "intID": 1248002006
        },
        {
          "Number": 7,
          "Content": " Բայց ընդհակառակը,  երբոր տեսան թէ անթլփատութեան աւետարանն  ինձ հաւատացուած է, ինչպէս Պետրոսին թլփատութեան աւետարանը. ",
          "ID": "b1t2b48c2v7",
          "intID": 1248002007
        },
        {
          "Number": 8,
          "Content": " (Որովհետեւ նա որ Պետրոսին յաջողեց թլփատութեան առաքելութիւնում,  ինձ էլ  յաջողեց հեթանոսների մէջ։) ",
          "ID": "b1t2b48c2v8",
          "intID": 1248002008
        },
        {
          "Number": 9,
          "Content": "  Եւ երբոր իմացան այն շնորհքը որ ինձ տրուած էր, Յակոբոսը եւ Կեփասը եւ Յովհաննէսը,  որ սիւներ էին կարծուած, ինձ եւ Բառնաբասին աջ ձեռը տուին հաղորդակցութեան համար. Որ մենք հեթանոսների մէջ լինենք, եւ նորանք թլփատութեան մէջ։ ",
          "ID": "b1t2b48c2v9",
          "intID": 1248002009
        },
        {
          "Number": 10,
          "Content": " Բայց միայն որ աղքատները յիշենք.  որ ես էլ ջանք արի նոյնն անելու։ ",
          "ID": "b1t2b48c2v10",
          "intID": 1248002010
        },
        {
          "Number": 11,
          "Content": "  Բայց երբ որ Պետրոսը եկաւ Անտիոք, ես նորան հակառակ կեցայ, որ մեղադրելի էր։ ",
          "ID": "b1t2b48c2v11",
          "intID": 1248002011
        },
        {
          "Number": 12,
          "Content": " Վասնզի մի քանի մարդիկ դեռ չ’եկած Յակոբիցը, նա  անխտիր ուտում էր հեթանոսների հետ. Բայց երբոր եկան, ետ էր քաշվում եւ իր անձը ջոկում, վախենալով նորանցից որ թլփատութիւնիցն էին։ ",
          "ID": "b1t2b48c2v12",
          "intID": 1248002012
        },
        {
          "Number": 13,
          "Content": " Եւ նորա հետ ուրիշ Հրէաներն էլ կեղծաւորութիւն արին. Մինչեւ որ Բառնաբասն էլ ծռուեցաւ նորանց կեղծաւորութիւնովը։ ",
          "ID": "b1t2b48c2v13",
          "intID": 1248002013
        },
        {
          "Number": 14,
          "Content": " Բայց երբոր տեսայ,  որ աւետարանի ճշմարտութեան համեմատ ուղիղ չեն գնում,  ամենքի առաջին ասեցի Պետրոսին.  Եթէ դու, Հրէայ լինելովդ, հեթանոսի պէս ես վարվում եւ ոչ թէ Հրէայի պէս, էլ ի՞նչու ես բռնադատում հեթանոսներին որ Հրէայի պէս վարուին։ ",
          "ID": "b1t2b48c2v14",
          "intID": 1248002014
        },
        {
          "Number": 15,
          "Content": "  Մենք որ բուն Հրէաներ ենք,  եւ ոչ թէ հեթանոսների միջից մեղաւորներ. ",
          "ID": "b1t2b48c2v15",
          "intID": 1248002015
        },
        {
          "Number": 16,
          "Content": "  Գիտենք որ մարդ օրէնքի գործերիցը չէ արդարանում,  բայց միայն Յիսուս Քրիստոսի հաւատքիցը. Եւ մենք Յիսուս Քրիստոսին հաւատացինք, որ Քրիստոսի հաւատքիցն արդարանանք, եւ ոչ թէ օրէնքի գործերիցը.  որովհետեւ օրէնքի գործերիցն ոչ մի մարմին չի արդարանալ։ ",
          "ID": "b1t2b48c2v16",
          "intID": 1248002016
        },
        {
          "Number": 17,
          "Content": " Իսկ եթէ մենք՝ որ ուզում ենք Քրիստոսով արդարանալ, ինքներս էլ  մեղաւոր գտնուինք, ուրեմն Քրիստոսը մեղքի՞ պաշտօնեայ է. Քաւ լիցի։ ",
          "ID": "b1t2b48c2v17",
          "intID": 1248002017
        },
        {
          "Number": 18,
          "Content": " Վասնզի՝ եթէ այն որ քանդեցի՝ նորան կրկին շինեմ, ապա ես ինքս իմ անձը մեղաւոր եմ երեւեցնում։ ",
          "ID": "b1t2b48c2v18",
          "intID": 1248002018
        },
        {
          "Number": 19,
          "Content": "  Որովհետեւ ես օրէնքովն օրէնքին  մեռայ,  որ ապրեմ Աստուծուն. Ես  Քրիստոսի հետ խաչուած եմ։ ",
          "ID": "b1t2b48c2v19",
          "intID": 1248002019
        },
        {
          "Number": 20,
          "Content": " Եւ կենդանի եմ, ոչ թէ այլ եւս ես, այլ Քրիստոս է կենդանի ինձանում. Եւ ինչ որ հիմա կենդանի եմ մարմնով՝  Աստուծոյ Որդու հաւատքովն եմ կենդանի.  որ ինձ սիրեց եւ իր անձը ինձ համար մատնեց։ ",
          "ID": "b1t2b48c2v20",
          "intID": 1248002020
        },
        {
          "Number": 21,
          "Content": " Եւ ես Աստուծոյ շնորհքը չեմ անարգում,  որովհետեւ եթէ արդարութիւնն օրէնքիցն էր, ուրեմն Քրիստոսը զուր տեղը մեռաւ։ \n",
          "ID": "b1t2b48c2v21",
          "intID": 1248002021
        }
      ],
      "ID": "b1t2b48c2",
      "intID": 1248002000,
      "HTML": null,
      "IsDownloaded": false,
      "IsProblematic": false,
      "Content": null
    },
    {
      "Number": 3,
      "Description": "Հաւատքով արդարանալ և ոչ թէ օրէնքով։ ",
      "Verses": [
        {
          "Number": 1,
          "Content": " Ով անմիտ Գաղատացիներ,  ո՞վ կախարդեց ձեզ որ ճշմարտութեանը չհնազանդիք. որոնց համար աչքերի առաջին նկարագրուեցաւ Յիսուս Քրիստոսը խաչուած ձեր մէջ։ ",
          "ID": "b1t2b48c3v1",
          "intID": 1248003001
        },
        {
          "Number": 2,
          "Content": " Այս միայն կամենում եմ սովորիլ ձեզանից.  օրէնքի գործերի՞ցն ընդունեցիք Հոգին՝  թէ հաւատքի լսելուցը։ ",
          "ID": "b1t2b48c3v2",
          "intID": 1248003002
        },
        {
          "Number": 3,
          "Content": " Այդքան անմի՞տ էք.  հոգով սկսեցիք,  եւ հիմա մարմնո՞վ էք վերջանում։ ",
          "ID": "b1t2b48c3v3",
          "intID": 1248003003
        },
        {
          "Number": 4,
          "Content": "  Այնքան նեղութիւններ զո՞ւր տեղը կրեցիք. թէ որ զուր էլ լինի։ ",
          "ID": "b1t2b48c3v4",
          "intID": 1248003004
        },
        {
          "Number": 5,
          "Content": "  Արդ ձեզ Հոգին բաժանողը եւ ձեր միջումը զօրութիւններ գործողը, օրէնքի գործերի՞ց է թէ հաւատքի լսելուցը։ ",
          "ID": "b1t2b48c3v5",
          "intID": 1248003005
        },
        {
          "Number": 6,
          "Content": "  Ինչպէս որ Աբրահամը հաւատաց Աստուծուն, եւ այն նորա համար արդարութիւն համարուեցաւ։ ",
          "ID": "b1t2b48c3v6",
          "intID": 1248003006
        },
        {
          "Number": 7,
          "Content": " Ուրեմն գիտացէք. թէ  նորանք որ հաւատքիցն են, նորանք են Աբրահամի որդիք։ ",
          "ID": "b1t2b48c3v7",
          "intID": 1248003007
        },
        {
          "Number": 8,
          "Content": "  Գիրքն էլ առաջուց գիտենալով, որ Աստուած հաւատքիցն է արդարացնում հեթանոսներին՝ առաջուց Աբրահամին խոստացաւ, թէ  Քեզանում պիտի օրհնուին բոլոր ազգերը։ ",
          "ID": "b1t2b48c3v8",
          "intID": 1248003008
        },
        {
          "Number": 9,
          "Content": " Ուրեմն նորանք որ հաւատքից են, օրհնվում են հաւատացեալ Աբրահամի հետ։ ",
          "ID": "b1t2b48c3v9",
          "intID": 1248003009
        },
        {
          "Number": 10,
          "Content": " Որովհետեւ որոնք որ օրէնքի գործերից են, անէծքի տակ են. վասնզի գրուած է թէ  Անիծեալ լինի ամեն մարդ, որ չէ կենում օրէնքի գրքի մէջի բոլոր գրուածներումը, որ ամենն անէ։ ",
          "ID": "b1t2b48c3v10",
          "intID": 1248003010
        },
        {
          "Number": 11,
          "Content": "  Եւ թէ օրէնքովն ոչ ով չէ արդարանում Աստուծոյ առաջին, դա յայտնի է. որովհետեւ  Արդարը հաւատքիցը կապրէ։ ",
          "ID": "b1t2b48c3v11",
          "intID": 1248003011
        },
        {
          "Number": 12,
          "Content": "  Բայց օրէնքը հաւատքիցը չէ այլ՝  Նորանց կատարող մարդը կապրէ նորանով։ ",
          "ID": "b1t2b48c3v12",
          "intID": 1248003012
        },
        {
          "Number": 13,
          "Content": "  Քրիստոս գնեց մեզ օրէնքի անէծքիցը մեզ համար անէծք լինելով. (վասնզի գրուած է թէ  Անիծեալ լինի ամեն փայտից կախուածը։) ",
          "ID": "b1t2b48c3v13",
          "intID": 1248003013
        },
        {
          "Number": 14,
          "Content": "  Որ Աբրահամի օրհնութիւնը հեթանոսների մէջ լինի Քրիստոս Յիսուսով,  որ մենք Սուրբ Հոգու խոստմունքն ընդունենք հաւատքով։ ",
          "ID": "b1t2b48c3v14",
          "intID": 1248003014
        },
        {
          "Number": 15,
          "Content": " Մարդկօրէն եմ ասում, եղբարք.  ապաքէն մի մարդի հաստատուած կտակը ոչ ով չէ անարգում. եւ ոչ էլ նորա վերայ ուրիշ հրաման աւելացնում։ ",
          "ID": "b1t2b48c3v15",
          "intID": 1248003015
        },
        {
          "Number": 16,
          "Content": "  Եւ Աբրահամին խոստացուեցան այն խոստմունքները, եւ նորա զաւակին. չէ ասում, Եւ զաւակներին՝ ինչպէս շատերին, այլ ինչպէս մէկին. Եւ քո զաւակին.  որ է Քրիստոսը։ ",
          "ID": "b1t2b48c3v16",
          "intID": 1248003016
        },
        {
          "Number": 17,
          "Content": " Բայց սա եմ ասում. Այն կտակը, որ առաջուց Աստուածանից հաստատուած էր Քրիստոսի վերայ,  չորս հարիւր եւ երեսուն տարուց յետոյ եղած օրէնքը  չի քանդիլ որ խոստմունքը խափանուի։ ",
          "ID": "b1t2b48c3v17",
          "intID": 1248003017
        },
        {
          "Number": 18,
          "Content": "  Որովհետեւ եթէ ժառանգութիւնն օրէնքից լիներ,  ապա խոստմունքից չէր. բայց Աստուած խոստմունքով շնորհեց Աբրահամին։ ",
          "ID": "b1t2b48c3v18",
          "intID": 1248003018
        },
        {
          "Number": 19,
          "Content": " Արդ օրէնքն ի՞նչ է.  նա յանցանքների պատճառով աւելացաւ.  մինչեւ որ գայ այն զաւակը, որին եղաւ խոստմունքը  հրեշտակներով կարգուած  միջնորդի ձեռով։ ",
          "ID": "b1t2b48c3v19",
          "intID": 1248003019
        },
        {
          "Number": 20,
          "Content": " Բայց միջնորդը մէկի չէ,  սակայն Աստուած մէկ է։ ",
          "ID": "b1t2b48c3v20",
          "intID": 1248003020
        },
        {
          "Number": 21,
          "Content": " Ուրեմն օրէնքը Աստուծոյ խոստմունքներին հակառա՞կ է. քաւ լիցի.  որովհետեւ եթէ օրէնք տրուած լինէր որ կարող լինէր կենդանի անել, ապա իրաւի օրէնքից կլինէր արդարութիւնը։ ",
          "ID": "b1t2b48c3v21",
          "intID": 1248003021
        },
        {
          "Number": 22,
          "Content": "  Բայց գիրքը  փակեց ամենքը մեղքի ներքեւ,  որ խոստմունքը Յիսուս Քրիստոսի հաւատքիցը տրուի հաւատացողներին։ ",
          "ID": "b1t2b48c3v22",
          "intID": 1248003022
        },
        {
          "Number": 23,
          "Content": " Դեռ որ հաւատքը չէր եկած՝ օրէնքի ներքեւ փակուած պահվում էինք այն հաւատքի համար, որ պէտք էր յայտնուէր։ ",
          "ID": "b1t2b48c3v23",
          "intID": 1248003023
        },
        {
          "Number": 24,
          "Content": "  Ուրեմն օրէնքը մեզ համար դաստիարակ եղաւ դէպի Յիսուս Քրիստոսը,  որ հաւատքից արդարանանք։ ",
          "ID": "b1t2b48c3v24",
          "intID": 1248003024
        },
        {
          "Number": 25,
          "Content": " Բայց երբոր հաւատքն եկաւ, այլեւս դաստիարակի տակ չենք։ ",
          "ID": "b1t2b48c3v25",
          "intID": 1248003025
        },
        {
          "Number": 26,
          "Content": "  Որովհետեւ ամենքդ Աստուծոյ որդիք էք Քրիստոս Յիսուսի հաւատքովը։ ",
          "ID": "b1t2b48c3v26",
          "intID": 1248003026
        },
        {
          "Number": 27,
          "Content": "  Վասնզի ամենքդ՝ որ Քրիստոսումը մկրտուեցաք,  Քրիստոսին հագած էք։ ",
          "ID": "b1t2b48c3v27",
          "intID": 1248003027
        },
        {
          "Number": 28,
          "Content": "  Այլ եւս ոչ Հրէայ կայ եւ ոչ Յոյն, ոչ ծառայ կայ եւ ոչ ազատ, ոչ արու կայ եւ ոչ էգ.  որովհետեւ դուք ամենքդ մէկ էք Քրիստոս Յիսուսումը։ ",
          "ID": "b1t2b48c3v28",
          "intID": 1248003028
        },
        {
          "Number": 29,
          "Content": "  Ապա եթէ դուք Քրիստոսինն էք, ուրեմն Աբրահամի զաւակ էք՝  եւ խոստմունքի համեմատ ժառանգներ։ \n",
          "ID": "b1t2b48c3v29",
          "intID": 1248003029
        }
      ],
      "ID": "b1t2b48c3",
      "intID": 1248003000,
      "HTML": null,
      "IsDownloaded": false,
      "IsProblematic": false,
      "Content": null
    },
    {
      "Number": 4,
      "Description": "Մարդիս վիճակը օրէնքի ներքև և շնորհքի ներքև։ Հագար և Սարրա։ ",
      "Verses": [
        {
          "Number": 1,
          "Content": " Բայց ասում եմ. քանի ժամանակ որ ժառանգը երեխայ է՝ ծառայից ոչինչ տարբերութիւն չունի, թէեւ ամեն բանի տէր է։ ",
          "ID": "b1t2b48c4v1",
          "intID": 1248004001
        },
        {
          "Number": 2,
          "Content": " Բայց վերակացուների եւ տնտեսների ներքեւ է մինչեւ հօր որոշած ժամանակը։ ",
          "ID": "b1t2b48c4v2",
          "intID": 1248004002
        },
        {
          "Number": 3,
          "Content": " Այնպէս էլ մենք, քանի որ երեխաներ էինք՝  աշխարհքի սկզբունքների ներքեւ ծառայութեան մէջ էինք։ ",
          "ID": "b1t2b48c4v3",
          "intID": 1248004003
        },
        {
          "Number": 4,
          "Content": "  Բայց երբոր ժամանակի լրումն եկաւ, Աստուած ուղարկեց իր Որդին՝  կնկանից  ծնուած՝  եւ օրէնքի ներքեւ եղած, ",
          "ID": "b1t2b48c4v4",
          "intID": 1248004004
        },
        {
          "Number": 5,
          "Content": "  Որ օրէնքի տակ լինողներին փրկէ,  որ որդեգրութիւնն ընդունենք։ ",
          "ID": "b1t2b48c4v5",
          "intID": 1248004005
        },
        {
          "Number": 6,
          "Content": " Եւ որովհետեւ դուք որդիք էք,  Աստուած իր Որդու Հոգին ուղարկեց ձեր սրտերի մէջ, որ աղաղակում է Աբբա Հայր։ ",
          "ID": "b1t2b48c4v6",
          "intID": 1248004006
        },
        {
          "Number": 7,
          "Content": " Ուրեմն այլ եւս ծառայ չես՝ այլ որդի.  եւ եթէ որդի՝ Աստուծոյ ժառանգ էլ Քրիստոսով։ ",
          "ID": "b1t2b48c4v7",
          "intID": 1248004007
        },
        {
          "Number": 8,
          "Content": "  Բայց այն ժամանակ որ Աստուծուն չգիտէիք,  ծառայում էիք նորանց որ ի բնէ աստուածներ չեն։ ",
          "ID": "b1t2b48c4v8",
          "intID": 1248004008
        },
        {
          "Number": 9,
          "Content": "  Բայց հիմա որ ճանաչեցիք Աստուծուն, մանաւանդ թէ Աստուածանից ճանաչուեցաք,  ի՞նչպէս էք կրկին ետ դառնում  դէպի այն տկար եւ աղքատ սկզբունքները, որոնց կամենում էք դարձեալ ծառայել։ ",
          "ID": "b1t2b48c4v9",
          "intID": 1248004009
        },
        {
          "Number": 10,
          "Content": "  Օրեր էք զանազանում եւ ամիսներ եւ ժամանակներ եւ տարիներ։ ",
          "ID": "b1t2b48c4v10",
          "intID": 1248004010
        },
        {
          "Number": 11,
          "Content": " Վախենում եմ ձեզանից՝  որ մի գուցէ զուր տեղն աշխատեցի ձեր միջումը։ \n",
          "ID": "b1t2b48c4v11",
          "intID": 1248004011
        },
        {
          "Number": 12,
          "Content": " Ինձ նման եղէք, որովհետեւ ես էլ ձեզ նման եմ. եղբարք, աղաչում եմ ձեզ,  դուք ինձ ոչ մի վնաս չէք տուել։ ",
          "ID": "b1t2b48c4v12",
          "intID": 1248004012
        },
        {
          "Number": 13,
          "Content": " Եւ գիտէք որ  մարմնի տկարութիւնով աւետարանեցի ձեզ  առաջի անգամը. ",
          "ID": "b1t2b48c4v13",
          "intID": 1248004013
        },
        {
          "Number": 14,
          "Content": " Եւ իմ փորձանքն՝ որ իմ մարմնումն էր, չանարգեցիք եւ չարհամարհեցիք,  այլ ինչպէս Աստուծոյ հրեշտակ ընդունեցիք ինձ՝  ինչպէս Քրիստոս Յիսուսին։ ",
          "ID": "b1t2b48c4v14",
          "intID": 1248004014
        },
        {
          "Number": 15,
          "Content": " Արդ ի՞նչ էր այն ձեր երանութիւնը. որովհետեւ վկայում եմ ձեզ համար, որ եթէ կարելի էր՝ ձեր աչքերն էլ կհանէիք եւ ինձ կտայիք։ ",
          "ID": "b1t2b48c4v15",
          "intID": 1248004015
        },
        {
          "Number": 16,
          "Content": " Ուրեմն թշնամի՞ եղայ ձեզ՝  ձեզ հետ ճշմարիտը խօսելովս։ ",
          "ID": "b1t2b48c4v16",
          "intID": 1248004016
        },
        {
          "Number": 17,
          "Content": "  Նախանձով են ձեզ համար, ոչ թէ ի բարին. այլ կամենում են արգելել մեզ որ նորանց համար նախանձաւոր լինիք։ ",
          "ID": "b1t2b48c4v17",
          "intID": 1248004017
        },
        {
          "Number": 18,
          "Content": " Սակայն լաւ է բարի բանում ամեն ժամանակ նախանձաւոր լինել, եւ ոչ թէ միայն երբ որ ձեզ մօտ լինեմ։ ",
          "ID": "b1t2b48c4v18",
          "intID": 1248004018
        },
        {
          "Number": 19,
          "Content": "  Իմ որդեակներ, որ ձեզ կրկին ծնում եմ ցաւով, մինչեւ որ Քրիստոսը կերպարանուի ձեզանում։ ",
          "ID": "b1t2b48c4v19",
          "intID": 1248004019
        },
        {
          "Number": 20,
          "Content": " Կամենում էի որ հիմա ձեզ մօտ գամ եւ ձայնս փոխեմ. Որովհետեւ տարակուսած եմ ձեզ համար։ \n",
          "ID": "b1t2b48c4v20",
          "intID": 1248004020
        },
        {
          "Number": 21,
          "Content": " Ասեցէք ինձ դուք, որ կամենում էք օրէնքի տակ լինել, օրէնքը չէ՞ք լսում։ ",
          "ID": "b1t2b48c4v21",
          "intID": 1248004021
        },
        {
          "Number": 22,
          "Content": " Որովհետեւ գրուած է, թէ Աբրահամը երկու որդիք ունէր,  մինն աղախնիցը,  եւ միւսն ազատիցը։ ",
          "ID": "b1t2b48c4v22",
          "intID": 1248004022
        },
        {
          "Number": 23,
          "Content": " Բայց նա որ աղախնիցն էր՝  մարմնի կողմանէ էր ծնուած,  եւ նա որ ազատիցն՝ խոստմունքի համեմատ։ ",
          "ID": "b1t2b48c4v23",
          "intID": 1248004023
        },
        {
          "Number": 24,
          "Content": " Այս բաները այլաբանօրէն են. որ նորանք երկու կտակարաններն են, մէկը  Սինա սարիցը ծառայութեան մէջ ծնուած՝ որ է Հագարը։ ",
          "ID": "b1t2b48c4v24",
          "intID": 1248004024
        },
        {
          "Number": 25,
          "Content": " Որովհետեւ Հագարը Սինա սարն է՝ Արաբիայումն, որ հաւասար է այժմեան Երուսաղէմին, որ իր զաւակներովը հանդերձ ծառայ է։ ",
          "ID": "b1t2b48c4v25",
          "intID": 1248004025
        },
        {
          "Number": 26,
          "Content": "  Բայց վերին Երուսաղէմն ազատ է, որ մեր ամենիս մայրն է։ ",
          "ID": "b1t2b48c4v26",
          "intID": 1248004026
        },
        {
          "Number": 27,
          "Content": " Որովհետեւ գրուած է թէ,  Ցնծա, ով ամուլ՝ որ չէիր ծնում, գոչիր եւ աղաղակիր դու՝ որ ծնելու ցաւ չէիր քաշում. որովհետեւ աւելի շատ են թողուածի որդիքը քան թէ արամբիինը։ ",
          "ID": "b1t2b48c4v27",
          "intID": 1248004027
        },
        {
          "Number": 28,
          "Content": " Իսկ մենք, եղբարք,  Իսահակի պէս խոստմունքի որդիք ենք։ ",
          "ID": "b1t2b48c4v28",
          "intID": 1248004028
        },
        {
          "Number": 29,
          "Content": "  Բայց ինչպէս որ այն ժամանակ մարմնի կողմանէ ծնուածը հալածում էր նորան՝ որ հոգու կողմանէ էր,  այնպէս էլ հիմա։ ",
          "ID": "b1t2b48c4v29",
          "intID": 1248004029
        },
        {
          "Number": 30,
          "Content": "  Բայց գի՞րքն ինչ է ասում.  Դուրս հանիր աղախնին ու նորա որդուն.  որ աղախնի որդին ժառանգութիւն չպիտի ստանայ ազատի որդու հետ։ ",
          "ID": "b1t2b48c4v30",
          "intID": 1248004030
        },
        {
          "Number": 31,
          "Content": " Սորա համար, եղբարք, աղախնի որդիք չենք,  այլ ազատի։ \n",
          "ID": "b1t2b48c4v31",
          "intID": 1248004031
        }
      ],
      "ID": "b1t2b48c4",
      "intID": 1248004000,
      "HTML": null,
      "IsDownloaded": false,
      "IsProblematic": false,
      "Content": null
    },
    {
      "Number": 5,
      "Description": "Աւետարանի ազատութեան գործածութիւնը։ Մարմնի գործերը և հոգու գործերը։ ",
      "Verses": [
        {
          "Number": 1,
          "Content": " Արդ  այն ազատութիւնովը որ Քրիստոսը մեզ ազատեց, հաստատ կացէք եւ  դարձեալ ծառայութեան լծի տակ մի մտնէք։ ",
          "ID": "b1t2b48c5v1",
          "intID": 1248005001
        },
        {
          "Number": 2,
          "Content": " Ահա ես Պօղոսս ասում եմ ձեզ,  որ եթէ թլփատուիք, Քրիստոսը ձեզ օգուտ չի անիլ։ ",
          "ID": "b1t2b48c5v2",
          "intID": 1248005002
        },
        {
          "Number": 3,
          "Content": " Եւ դարձեալ վկայում եմ ամեն մարդի համար որ թլփատվում է, թէ  նա պարտական է բոլոր օրէնքը կատարելու։ ",
          "ID": "b1t2b48c5v3",
          "intID": 1248005003
        },
        {
          "Number": 4,
          "Content": "  Խափանուած էք Քրիստոսից դուք, որ օրէնքով էք կամենում արդարանալ.  շնորհքիցն ընկած էք։ ",
          "ID": "b1t2b48c5v4",
          "intID": 1248005004
        },
        {
          "Number": 5,
          "Content": "  Որովհետեւ մենք Հոգով հաւատքիցն ենք սպասում արդարութեան յոյսին։ ",
          "ID": "b1t2b48c5v5",
          "intID": 1248005005
        },
        {
          "Number": 6,
          "Content": "  Վասնզի Քրիստոս Յիսուսումը ոչ թլփատութինն է մի բան կարող, եւ ոչ անթլփատութիւնը.  այլ հաւատքը որ սիրով գործում է։ ",
          "ID": "b1t2b48c5v6",
          "intID": 1248005006
        },
        {
          "Number": 7,
          "Content": "  Լաւ էիք վազում,  ձեզ ո՞վ ետ կանգնեցրեց՝ որ չհնազանդիք ճշմարտութեանը։ ",
          "ID": "b1t2b48c5v7",
          "intID": 1248005007
        },
        {
          "Number": 8,
          "Content": " Այդ համոզումը նորանից չէ  որ կանչեց ձեզ։ ",
          "ID": "b1t2b48c5v8",
          "intID": 1248005008
        },
        {
          "Number": 9,
          "Content": "  Մի քիչ խմորը բոլոր զանգուածը խմորեցնում է։ ",
          "ID": "b1t2b48c5v9",
          "intID": 1248005009
        },
        {
          "Number": 10,
          "Content": "  Ես ձեզ վերայ յոյս ունիմ Տէրովը՝ որ ուրիշ բան չէք մտածիլ.  եւ ձեզ խռովեցնողը  դատապարտութիւն կքաշէ ով որ էլ լինի։ ",
          "ID": "b1t2b48c5v10",
          "intID": 1248005010
        },
        {
          "Number": 11,
          "Content": "  Բայց ես, եղբարք, եթէ տակաւին թլփատութիւն եմ քարոզում,  էլ ի՞նչու համար եմ հալածվում.  ուրեմն խաչի գայթակղութիւնը խափանուած է։ ",
          "ID": "b1t2b48c5v11",
          "intID": 1248005011
        },
        {
          "Number": 12,
          "Content": "  Երանի թէ բոլորովին կտրուէին նորանք  որ ձեզ խռովեցնում են։ \n",
          "ID": "b1t2b48c5v12",
          "intID": 1248005012
        },
        {
          "Number": 13,
          "Content": " Որովհետեւ դուք ազատութեան համար էք կանչուել, եղբարք.  միայն թէ ձեր ազատութիւնը պատճառ չտայ մարմնին.  այլ սիրով ծառայեցէք իրար։ ",
          "ID": "b1t2b48c5v13",
          "intID": 1248005013
        },
        {
          "Number": 14,
          "Content": "  Որովհետեւ բոլոր օրէնքն այս մէկ խօսքումն է կատարվում.  Քո ընկերին քո անձի պէս սիրիր։ ",
          "ID": "b1t2b48c5v14",
          "intID": 1248005014
        },
        {
          "Number": 15,
          "Content": " Բայց եթէ իրար կծէք եւ ուտէք, զգուշացէք որ իրարից չփչանաք։ ",
          "ID": "b1t2b48c5v15",
          "intID": 1248005015
        },
        {
          "Number": 16,
          "Content": " Բայց ասում եմ.  Հոգով գնացէք, եւ մարմնի ցանկութիւնը չէք կատարիլ։ ",
          "ID": "b1t2b48c5v16",
          "intID": 1248005016
        },
        {
          "Number": 17,
          "Content": "  Որովհետեւ մարմինը ցանկանում է հոգուն հակառակ, եւ հոգին մարմնին հակառակ. եւ սորանք իրար հակառակ են,  որ մի գուցէ այն որ դուք կամենում էք՝ այն անէք։ ",
          "ID": "b1t2b48c5v17",
          "intID": 1248005017
        },
        {
          "Number": 18,
          "Content": "  Բայց եթէ Հոգուց էք առաջնորդվում, օրէնքի տակ չէք. ",
          "ID": "b1t2b48c5v18",
          "intID": 1248005018
        },
        {
          "Number": 19,
          "Content": "  Եւ յայտնի են մարմնի գործերը, որ են՝ շնութիւն, պոռնկութիւն, պղծութիւն, գիջութիւն, ",
          "ID": "b1t2b48c5v19",
          "intID": 1248005019
        },
        {
          "Number": 20,
          "Content": " Կռապաշտութիւն, կախարդութիւն, թշնամութիւններ, կռիւներ, նախանձներ, բարկութիւններ, հակառակութիւններ, երկպառակութիններ, բաժանմունքներ, ",
          "ID": "b1t2b48c5v20",
          "intID": 1248005020
        },
        {
          "Number": 21,
          "Content": " Չար նայուածներ, սպանութիւններ, արբեցութիւններ, անառակութիւններ, եւ ինչ որ սորանց նման են. որ առաջուց ասում եմ ձեզ, ինչպէս էլ առաջուց ասում էի, թէ  այսպիսի բաներ գործողներն Աստուծոյ արքայութիւնը չեն ժառանգիլ։ ",
          "ID": "b1t2b48c5v21",
          "intID": 1248005021
        },
        {
          "Number": 22,
          "Content": "  Բայց հոգու պտուղն է՝ սէր, ուրախութիւն, խաղաղութիւն, երկայնմտութիւն, ",
          "ID": "b1t2b48c5v22",
          "intID": 1248005022
        },
        {
          "Number": 23,
          "Content": "  Քաղցրութիւն,  բարութիւն,  հաւատք, հեզութիւն, ժուժկալութիւն.  այնպիսիների դէմ օրէնք չ’կայ։ ",
          "ID": "b1t2b48c5v23",
          "intID": 1248005023
        },
        {
          "Number": 24,
          "Content": " Բայց նորանք որ Քրիստոսինն են,  իրանց մարմինը խաչ հանեցին կիրքերովը եւ ցանկութիւններովը միասին։ ",
          "ID": "b1t2b48c5v24",
          "intID": 1248005024
        },
        {
          "Number": 25,
          "Content": "  Եթէ Հոգով ենք ապրում, Հոգով վարուինք։ ",
          "ID": "b1t2b48c5v25",
          "intID": 1248005025
        },
        {
          "Number": 26,
          "Content": "  Սնապարծ չլինինք իրար գրգռելով, եւ իրար վերայ նախանձելով։ \n",
          "ID": "b1t2b48c5v26",
          "intID": 1248005026
        }
      ],
      "ID": "b1t2b48c5",
      "intID": 1248005000,
      "HTML": null,
      "IsDownloaded": false,
      "IsProblematic": false,
      "Content": null
    },
    {
      "Number": 6,
      "Description": "Ողորմած և ներողամիտ լինելու յորդոր։ ",
      "Verses": [
        {
          "Number": 1,
          "Content": " Եղբարք,  եթէ մէկը յանկարծ բռնուի մի յանցանքով,  դուք որ հոգեւոր էք,  այնպիսին հաստատեցէք հեզութեան հոգով, զգուշացիր քո անձին,  որ դու էլ չփորձուիս։ ",
          "ID": "b1t2b48c6v1",
          "intID": 1248006001
        },
        {
          "Number": 2,
          "Content": "  Իրար բեռը վեր առէք,  եւ այսպէս Քրիստոսի օրէնքը կատարեցէք։ ",
          "ID": "b1t2b48c6v2",
          "intID": 1248006002
        },
        {
          "Number": 3,
          "Content": "  Որովհետեւ եթէ մէկը համարում է թէ մին բան է եւ  չէ, նա իր անձը խաբում է։ ",
          "ID": "b1t2b48c6v3",
          "intID": 1248006003
        },
        {
          "Number": 4,
          "Content": "  Բայց ամեն մէկը թող իր գործը կշռէ, եւ ապա միայն իր անձի վերայ պարծանք կունենայ,  եւ ոչ թէ ուրիշի վերայ. ",
          "ID": "b1t2b48c6v4",
          "intID": 1248006004
        },
        {
          "Number": 5,
          "Content": "  Որ ամեն մէկն իր բեռը պիտի վեր առնէ։ \n",
          "ID": "b1t2b48c6v5",
          "intID": 1248006005
        },
        {
          "Number": 6,
          "Content": "  Խօսքին աշակերտողը թող վարդապետին մասնակից անէ ամեն բարի բաներով։ ",
          "ID": "b1t2b48c6v6",
          "intID": 1248006006
        },
        {
          "Number": 7,
          "Content": "  Մի խաբուիք.  Աստուած չի ծաղրուիլ։ ",
          "ID": "b1t2b48c6v7",
          "intID": 1248006007
        },
        {
          "Number": 8,
          "Content": "  Որովհետեւ ինչ որ մարդ սերմէ, այն էլ կհնձէ.  իր մարմնի մէջ սերմողը մարմնիցն ապականութիւն կ’հնձէ. եւ Հոգու մէջ սերմողը Հոգուցն յաւիտենական կեանք կհնձէ։ ",
          "ID": "b1t2b48c6v8",
          "intID": 1248006008
        },
        {
          "Number": 9,
          "Content": "  Եւ չձանձրանաք բարին գործելուցը,  որովհետեւ իր ժամանակին կհնձենք՝ եթէ չթուլանանք։ ",
          "ID": "b1t2b48c6v9",
          "intID": 1248006009
        },
        {
          "Number": 10,
          "Content": "  Ուրեմն քանի որ ժամանակ ունինք,  բարի գործենք ամենին,  մանաւանդ հաւատքի ընտանիներին։ \n",
          "ID": "b1t2b48c6v10",
          "intID": 1248006010
        },
        {
          "Number": 11,
          "Content": " Տեսէք թէ ինչպիսի գրերով գրեցի ձեզ իմ ձեռովը։ ",
          "ID": "b1t2b48c6v11",
          "intID": 1248006011
        },
        {
          "Number": 12,
          "Content": " Որոնք որ կամենում են հաճոյ երեւել մարմնի կողմանէ,  նորանք ստիպում են ձեզ՝ որ թլփատուիք.  միայն որ  Քրիստոսի խաչի համար չհալածուին։ ",
          "ID": "b1t2b48c6v12",
          "intID": 1248006012
        },
        {
          "Number": 13,
          "Content": " Որովհետեւ այն թլփատուածներն իրանք էլ օրէնքը չեն պահում. այլ կամենում են որ դուք թլփատուիք, որ ձեր մարմնովը պարծենան։ ",
          "ID": "b1t2b48c6v13",
          "intID": 1248006013
        },
        {
          "Number": 14,
          "Content": "  Սակայն ինձ քաւ լիցի պարծենալ, բայց միայն մեր Տէր Յիսուս Քրիստոսի խաչովն.  որ նորանով աշխարհքն ինձ համար խաչուած է, եւ ես էլ աշխարհքին։ ",
          "ID": "b1t2b48c6v14",
          "intID": 1248006014
        },
        {
          "Number": 15,
          "Content": "  Որովհետեւ Քրիստոս Յիսուսումը ոչ թլփատութիւնը մի բան է, եւ ոչ անթլփատութիւնը,  բայց նոր արարածը։ ",
          "ID": "b1t2b48c6v15",
          "intID": 1248006015
        },
        {
          "Number": 16,
          "Content": "  Եւ այն ամենն  որ այս կանոնի համեմատ են վարվում, խաղաղութիւն լինի նորանց վերայ եւ ողորմութիւն, եւ  Աստուծոյ Իսրայէլին վերայ։ ",
          "ID": "b1t2b48c6v16",
          "intID": 1248006016
        },
        {
          "Number": 17,
          "Content": " Սորանից յետոյ թող մէկը չաշխատեցնէ ինձ.  որ ես կրում եմ Տէր Յիսուսի վէրքի նշաններն իմ մարմնի մէջ։ ",
          "ID": "b1t2b48c6v17",
          "intID": 1248006017
        },
        {
          "Number": 18,
          "Content": "  Մեր Տէր Յիսուս Քրիստոսի շնորհքը, եղբարք, ձեր հոգու հետ լինի. Ամէն։ \n",
          "ID": "b1t2b48c6v18",
          "intID": 1248006018
        }
      ],
      "ID": "b1t2b48c6",
      "intID": 1248006000,
      "HTML": null,
      "IsDownloaded": false,
      "IsProblematic": false,
      "Content": null
    }
  ],
  "ID": "b1t2b48",
  "intID": 1248000000,
  "GroupName": "Պողոսի թղթեր",
  "ChapterCount": 0,
  "HTML": null,
  "ShortNames": [
    "Գաղ."
  ],
  "PreferredShortName": "Գաղ."
}